panel_highcharts/__init__.py
panel_highcharts/bokeh.ext.json
panel_highcharts/charts.py
panel_highcharts/config.py
panel_highcharts/index.ts
panel_highcharts/package-lock.json
panel_highcharts/package.json
panel_highcharts/tsconfig.json
panel_highcharts/cli/__init__.py
panel_highcharts/dist/panel_highcharts.js
panel_highcharts/dist/panel_highcharts.js.map
panel_highcharts/dist/panel_highcharts.json
panel_highcharts/dist/panel_highcharts.min.js
panel_highcharts/dist/lib/index.d.ts
panel_highcharts/dist/lib/index.js
panel_highcharts/dist/lib/index.js.map
panel_highcharts/dist/lib/models/highbase.d.ts
panel_highcharts/dist/lib/models/highbase.js
panel_highcharts/dist/lib/models/highbase.js.map
panel_highcharts/dist/lib/models/highchart.d.ts
panel_highcharts/dist/lib/models/highchart.js
panel_highcharts/dist/lib/models/highchart.js.map
panel_highcharts/dist/lib/models/highgantt.d.ts
panel_highcharts/dist/lib/models/highgantt.js
panel_highcharts/dist/lib/models/highgantt.js.map
panel_highcharts/dist/lib/models/highmap.d.ts
panel_highcharts/dist/lib/models/highmap.js
panel_highcharts/dist/lib/models/highmap.js.map
panel_highcharts/dist/lib/models/highstock.d.ts
panel_highcharts/dist/lib/models/highstock.js
panel_highcharts/dist/lib/models/highstock.js.map
panel_highcharts/dist/lib/models/index.d.ts
panel_highcharts/dist/lib/models/index.js
panel_highcharts/dist/lib/models/index.js.map
panel_highcharts/models/__init__.py
panel_highcharts/models/highbase.py
panel_highcharts/models/highbase.ts
panel_highcharts/models/highchart.py
panel_highcharts/models/highchart.ts
panel_highcharts/models/highgantt.py
panel_highcharts/models/highgantt.ts
panel_highcharts/models/highmap.py
panel_highcharts/models/highmap.ts
panel_highcharts/models/highstock.py
panel_highcharts/models/highstock.ts
panel_highcharts/models/index.ts
panel_highcharts-20221018.1.dist-info/LICENSE
panel_highcharts-20221018.1.dist-info/METADATA
panel_highcharts-20221018.1.dist-info/WHEEL
panel_highcharts-20221018.1.dist-info/top_level.txt
panel_highcharts-20221018.1.dist-info/RECORD
